star_allele_comp/__init__.py
star_allele_comp/command.py
star_allele_comp/comparison.py
star_allele_comp/plot.py
star_allele_comp/py.typed
star_allele_comp/summary.py
star_allele_comp-0.2.dist-info/LICENSE
star_allele_comp-0.2.dist-info/METADATA
star_allele_comp-0.2.dist-info/WHEEL
star_allele_comp-0.2.dist-info/entry_points.txt
star_allele_comp-0.2.dist-info/top_level.txt
star_allele_comp-0.2.dist-info/RECORD
