Metadata-Version: 2.1
Name: star-allele-comp
Version: 0.2
Summary: Utility to compare star alleles
Author: linnil1
License: MIT License
Project-URL: repository, https://github.com/linnil1/star_alleles_comparator
Project-URL: homepage, https://github.com/linnil1/star_alleles_comparator
Project-URL: Homepage, https://github.com/linnil1/star_alleles_comparator
Keywords: HLA,KIR,comparator,allele,star-allele
Classifier: Development Status :: 3 - Alpha
Classifier: Programming Language :: Python :: 3
Classifier: Programming Language :: Python :: 3.10
Classifier: Programming Language :: Python :: 3.11
Classifier: License :: OSI Approved :: MIT License
Classifier: Typing :: Typed
Requires-Python: >=3.10
License-File: LICENSE
Requires-Dist: pandas
Requires-Dist: pandas-stubs
Requires-Dist: plotly
Requires-Dist: kaleido
